python_cli_example/__init__.py
python_cli_example/main.py
python_cli_example-0.1.0.dist-info/LICENSE
python_cli_example-0.1.0.dist-info/METADATA
python_cli_example-0.1.0.dist-info/WHEEL
python_cli_example-0.1.0.dist-info/entry_points.txt
python_cli_example-0.1.0.dist-info/RECORD
